{
  "date": "2026-05-27",
  "instrument": "SENSEX",
  "trades": [
    {
      "id": 23,
      "instrument": "SENSEX",
      "side": "",
      "entrySymbol": "",
      "entryTime": "09:33",
      "exitTime": "",
      "lots": 15,
      "lotSize": 20,
      "entryPrice": 266.6,
      "exitPrice": 197,
      "exitSL": 230.5,
      "exitNSL": 197,
      "tgtPts": -36,
      "charges": 200,
      "notes": "SL Hit"
    },
    {
      "id": 24,
      "instrument": "SENSEX",
      "side": "",
      "entrySymbol": "",
      "entryTime": "10:09",
      "exitTime": "",
      "lots": 15,
      "lotSize": 20,
      "entryPrice": 275.5,
      "exitPrice": 253.9,
      "exitSL": 253.9,
      "exitNSL": 253.9,
      "tgtPts": 70,
      "charges": 200,
      "notes": "Price Reach upto 74 points"
    },
    {
      "id": 25,
      "instrument": "SENSEX",
      "side": "",
      "entrySymbol": "",
      "entryTime": "10:52",
      "exitTime": "",
      "lots": 15,
      "lotSize": 20,
      "entryPrice": 278.6,
      "exitPrice": 254.95,
      "exitSL": 254.95,
      "exitNSL": 254.95,
      "tgtPts": 70,
      "charges": 200,
      "notes": "Price Reach upto 96 points"
    },
    {
      "id": 26,
      "instrument": "SENSEX",
      "side": "",
      "entrySymbol": "",
      "entryTime": "11:53",
      "exitTime": "",
      "lots": 15,
      "lotSize": 20,
      "entryPrice": 289.35,
      "exitPrice": 281.1,
      "exitSL": 281.1,
      "exitNSL": 281.1,
      "tgtPts": -8.25,
      "charges": 200,
      "notes": "Pine Script SL Hit"
    },
    {
      "id": 27,
      "instrument": "SENSEX",
      "side": "",
      "entrySymbol": "",
      "entryTime": "11:59",
      "exitTime": "",
      "lots": 15,
      "lotSize": 20,
      "entryPrice": 228.15,
      "exitPrice": 230.25,
      "exitSL": 230.25,
      "exitNSL": 230.25,
      "tgtPts": 70,
      "charges": 200,
      "notes": "price reach upto 74 points"
    },
    {
      "id": 28,
      "instrument": "SENSEX",
      "side": "",
      "entrySymbol": "",
      "entryTime": "12:52",
      "exitTime": "",
      "lots": 15,
      "lotSize": 20,
      "entryPrice": 260.6,
      "exitPrice": 260,
      "exitSL": 260,
      "exitNSL": 260,
      "tgtPts": 70,
      "charges": 200,
      "notes": "price reach upto 78 points"
    },
    {
      "id": 29,
      "instrument": "SENSEX",
      "side": "",
      "entrySymbol": "",
      "entryTime": "13:17",
      "exitTime": "",
      "lots": 15,
      "lotSize": 20,
      "entryPrice": 226.4,
      "exitPrice": 173.4,
      "exitSL": 189.9,
      "exitNSL": 173.4,
      "tgtPts": -36,
      "charges": 200,
      "notes": "SL Hit"
    },
    {
      "id": 30,
      "instrument": "SENSEX",
      "side": "",
      "entrySymbol": "",
      "entryTime": "13:47",
      "exitTime": "",
      "lots": 15,
      "lotSize": 20,
      "entryPrice": 238.1,
      "exitPrice": 171.6,
      "exitSL": 202.9,
      "exitNSL": 171.6,
      "tgtPts": -35,
      "charges": 200,
      "notes": "SL Hit"
    },
    {
      "id": 31,
      "instrument": "SENSEX",
      "side": "",
      "entrySymbol": "",
      "entryTime": "14:32",
      "exitTime": "",
      "lots": 15,
      "lotSize": 20,
      "entryPrice": 160.15,
      "exitPrice": 162.75,
      "exitSL": 162.75,
      "exitNSL": 162.75,
      "tgtPts": 70,
      "charges": 200,
      "notes": "price reach upto  106 points"
    }
  ]
}