{
  "date": "2026-06-22",
  "instrument": "NIFTY",
  "strategy": "bias",
  "trades": [
    {
      "id": 1,
      "instrument": "NIFTY",
      "side": "PE",
      "entrySymbol": "NIFTY260623P24250",
      "exitSymbol": "NIFTY260623P24250",
      "entryTime": "10:11",
      "exitTime": "12:02:26",
      "exitType": "target",
      "lots": 10,
      "lotSize": 65,
      "entryPrice": 143.25,
      "exitPrice": 144.15,
      "exitSL": 140.25,
      "exitTgt": 128.25,
      "exitNSL": 146.55,
      "tgtPts": -15,
      "maxReach": 0,
      "notes": "SL HIT",
      "time": "10:11",
      "candleRange": null,
      "pbNotes": "",
      "pbEntry": null,
      "pbTgtPts": null,
      "pbExitSL": null,
      "pbExitTgt": null,
      "slTarget": -3
    },
    {
      "id": 2,
      "instrument": "NIFTY",
      "side": "CE",
      "entrySymbol": "NIFTY260623C24000",
      "exitSymbol": "NIFTY260623C24050",
      "entryTime": "12:40",
      "exitTime": "13:05:31",
      "exitType": "exit",
      "lots": 10,
      "lotSize": 65,
      "entryPrice": 156.4,
      "exitPrice": 113.2,
      "exitSL": 156.4,
      "exitTgt": 148.1,
      "exitNSL": 148.1,
      "tgtPts": null,
      "maxReach": 4.1,
      "notes": "SL HIT",
      "time": "12:40",
      "candleRange": null,
      "pbNotes": "",
      "pbEntry": null,
      "pbTgtPts": null,
      "pbExitSL": null,
      "pbExitTgt": null,
      "slTarget": 0
    },
    {
      "id": 3,
      "instrument": "NIFTY",
      "side": "PE",
      "entrySymbol": "NIFTY260623P24200",
      "exitSymbol": "NIFTY260623P24200",
      "entryTime": "13:51",
      "exitTime": "14:31:33",
      "exitType": "exit",
      "lots": 10,
      "lotSize": 65,
      "entryPrice": 112.25,
      "exitPrice": 97.05,
      "exitSL": 112.25,
      "exitTgt": 97.2,
      "exitNSL": 97.25,
      "tgtPts": null,
      "maxReach": 21.9,
      "notes": "SL HIT",
      "time": "13:51",
      "candleRange": null,
      "pbNotes": "",
      "pbEntry": null,
      "pbTgtPts": null,
      "pbExitSL": null,
      "pbExitTgt": null,
      "slTarget": 0
    },
    {
      "id": 4,
      "instrument": "NIFTY",
      "side": "PE",
      "entrySymbol": "NIFTY260623P24250",
      "exitSymbol": "NIFTY260623P24250",
      "entryTime": "14:32",
      "exitTime": "15:07:33",
      "exitType": "exit",
      "lots": 10,
      "lotSize": 65,
      "entryPrice": 136.9,
      "exitPrice": 153.9,
      "exitSL": 136.9,
      "exitTgt": 152.45,
      "exitNSL": 152.45,
      "tgtPts": null,
      "maxReach": 21.9,
      "notes": "price reach upto 21.9 points",
      "time": "14:32",
      "candleRange": null,
      "pbNotes": "",
      "pbEntry": null,
      "pbTgtPts": null,
      "pbExitSL": null,
      "pbExitTgt": null,
      "slTarget": 0
    }
  ],
  "note": "vix  open: 12.970   low : 12.65 high : 13.51 close: 12.81"
}