{
  "date": "2026-06-17",
  "instrument": "SENSEX",
  "trades": [
    {
      "id": 1,
      "instrument": "SENSEX",
      "side": "CE",
      "entrySymbol": "BSX260618C76700",
      "exitSymbol": "BSX260618C76800",
      "entryTime": "09:32",
      "exitTime": "10:05:00",
      "lots": 15,
      "lotSize": 20,
      "entryPrice": 445.6,
      "exitPrice": null,
      "exitSL": 545.6,
      "exitNSL": 492.7,
      "tgtPts": 70,
      "maxReach": 0,
      "candleRange": 19,
      "notes": "price reach upto 118 points",
      "time": "09:32",
      "exitTgt": 515.6,
      "pbNotes": "",
      "pbEntry": null,
      "pbTgtPts": null,
      "pbExitSL": null,
      "pbExitTgt": null
    },
    {
      "id": 2,
      "instrument": "SENSEX",
      "side": "CE",
      "entrySymbol": "BSX260618C76900",
      "exitSymbol": "BSX260618C76900",
      "entryTime": "10:23",
      "exitTime": "11:05:00",
      "lots": 15,
      "lotSize": 20,
      "entryPrice": 413.65,
      "exitPrice": 403.05,
      "exitSL": 403.05,
      "exitNSL": 403.05,
      "tgtPts": -10.6,
      "maxReach": 0,
      "candleRange": 13,
      "notes": "price reach upto 42 points",
      "time": "10:23",
      "exitTgt": 403.05,
      "pbNotes": "",
      "pbEntry": null,
      "pbTgtPts": null,
      "pbExitSL": null,
      "pbExitTgt": null
    },
    {
      "id": 3,
      "instrument": "SENSEX",
      "side": "CE",
      "entrySymbol": "BSX260618C76900",
      "exitSymbol": "BSX260618C76900",
      "entryTime": "11:23:01",
      "exitTime": "11:38:00",
      "lots": 15,
      "lotSize": 20,
      "entryPrice": 426.25,
      "exitPrice": 418.3,
      "exitSL": 418.3,
      "exitTgt": 496.25,
      "exitNSL": 418.3,
      "tgtPts": -7.95,
      "maxReach": 33.75,
      "candleRange": 6.6,
      "notes": "price reach upto 33.75 points"
    },
    {
      "id": 4,
      "instrument": "SENSEX",
      "side": "PE",
      "entrySymbol": "BSX260618P77300",
      "exitSymbol": "BSX260618P77300",
      "entryTime": "12:00:00",
      "exitTime": "12:44:01",
      "lots": 15,
      "lotSize": 20,
      "entryPrice": 432,
      "exitPrice": 420,
      "exitSL": 420,
      "exitTgt": 502,
      "exitNSL": 420,
      "tgtPts": -12,
      "maxReach": 34.4,
      "candleRange": 14.25,
      "notes": "price reach upto 34.4 points"
    },
    {
      "id": 5,
      "instrument": "SENSEX",
      "side": "PE",
      "entrySymbol": "BSX260618P77200",
      "exitSymbol": "BSX260618P77200",
      "entryTime": "12:56:00",
      "exitTime": "13:21:00",
      "lots": 15,
      "lotSize": 20,
      "entryPrice": 397.65,
      "exitPrice": 382.9,
      "exitSL": 382.9,
      "exitTgt": 467.65,
      "exitNSL": 382.9,
      "tgtPts": -14.75,
      "maxReach": 36.5,
      "candleRange": 18.25,
      "notes": "price reach upto 36.5 points"
    },
    {
      "id": 6,
      "instrument": "SENSEX",
      "side": "CE",
      "entrySymbol": "BSX260618C76800",
      "exitSymbol": "BSX260618C76800",
      "entryTime": "13:36:00",
      "exitTime": "13:51:00",
      "lots": 15,
      "lotSize": 20,
      "entryPrice": 426.25,
      "exitPrice": 391.1,
      "exitSL": 391.25,
      "exitTgt": 496.25,
      "exitNSL": 391.1,
      "tgtPts": -35,
      "maxReach": 20.55,
      "candleRange": 26.35,
      "notes": "price reach upto 20.55 points"
    },
    {
      "id": 7,
      "instrument": "SENSEX",
      "side": "CE",
      "entrySymbol": "BSX260618C76900",
      "exitSymbol": "BSX260618C76900",
      "entryTime": "14:01:00",
      "exitTime": "14:11:01",
      "lots": 15,
      "lotSize": 20,
      "entryPrice": 357.95,
      "exitPrice": 323.45,
      "exitSL": 323.45,
      "exitTgt": 427.95,
      "exitNSL": 323.45,
      "tgtPts": -34.5,
      "maxReach": 4.2,
      "candleRange": 8.4,
      "notes": "PINE SCRIPT SL"
    },
    {
      "id": 8,
      "instrument": "SENSEX",
      "side": "CE",
      "entrySymbol": "BSX260618C76800",
      "exitSymbol": "BSX260618C76800",
      "entryTime": "14:40:01",
      "exitTime": "15:26:00",
      "lots": 15,
      "lotSize": 20,
      "entryPrice": 399.35,
      "exitPrice": 470.35,
      "exitSL": 499.35,
      "exitTgt": 469.35,
      "exitNSL": 470.35,
      "tgtPts": 70,
      "maxReach": 108.7,
      "candleRange": 8.5,
      "notes": "price reach upto 108.7 points"
    }
  ],
  "note": ""
}